botPlus/__init__.py
botPlus/botPlus.py
botPlus-1.2.3.dist-info/LICENSE
botPlus-1.2.3.dist-info/METADATA
botPlus-1.2.3.dist-info/WHEEL
botPlus-1.2.3.dist-info/top_level.txt
botPlus-1.2.3.dist-info/RECORD
