Metadata-Version: 2.1
Name: botPlus
Version: 1.2.3
Summary: Set up a Python Discord bot quickly!
Home-page: UNKNOWN
Author: OreoDivision
Author-email: <bobgim20@gmail.com>
License: UNKNOWN
Keywords: python,discord,discord.py,bot,discord bot,quick
Platform: UNKNOWN
Classifier: Development Status :: 1 - Planning
Classifier: Intended Audience :: Developers
Classifier: Programming Language :: Python :: 3
Classifier: Operating System :: Microsoft :: Windows
Requires-Dist: discord.py
Requires-Dist: colorama
